mamamiya/VERSION.txt
mamamiya/__init__.py
mamamiya/bond/__init__.py
mamamiya/bond/bonds.py
mamamiya/coins/__init__.py
mamamiya/coins/market.py
mamamiya/data/__init__.py
mamamiya/fund/__init__.py
mamamiya/fund/cons.py
mamamiya/fund/nav.py
mamamiya/futures/__init__.py
mamamiya/futures/cons.py
mamamiya/futures/domestic.py
mamamiya/futures/domestic_cons.py
mamamiya/futures/intlfutures.py
mamamiya/internet/__init__.py
mamamiya/internet/boxoffice.py
mamamiya/internet/caixinnews.py
mamamiya/internet/indexes.py
mamamiya/pro/__init__.py
mamamiya/pro/client.py
mamamiya/pro/data_pro.py
mamamiya/stock/__init__.py
mamamiya/stock/billboard.py
mamamiya/stock/classifying.py
mamamiya/stock/cons.py
mamamiya/stock/fundamental.py
mamamiya/stock/globals.py
mamamiya/stock/indictor.py
mamamiya/stock/macro.py
mamamiya/stock/macro_vars.py
mamamiya/stock/news_vars.py
mamamiya/stock/newsevent.py
mamamiya/stock/ref_vars.py
mamamiya/stock/reference.py
mamamiya/stock/shibor.py
mamamiya/stock/trading.py
mamamiya/stock/trendline.py
mamamiya/trader/__init__.py
mamamiya/trader/trader.py
mamamiya/trader/utils.py
mamamiya/trader/vars.py
mamamiya/util/__init__.py
mamamiya/util/common.py
mamamiya/util/conns.py
mamamiya/util/dateu.py
mamamiya/util/formula.py
mamamiya/util/mailmerge.py
mamamiya/util/netbase.py
mamamiya/util/store.py
mamamiya/util/upass.py
mamamiya/util/vars.py
test/__init__.py
test/bar_test.py
test/billboard_test.py
test/classifying_test.py
test/dateu_test.py
test/fund_test.py
test/indictor_test.py
test/macro_test.py
test/nav_test.py
test/news_test.py
test/ref_test.py
test/shibor_test.py
test/storing_test.py
test/trading_test.py
mamamiya-1.3.2.dist-info/LICENSE
mamamiya-1.3.2.dist-info/METADATA
mamamiya-1.3.2.dist-info/WHEEL
mamamiya-1.3.2.dist-info/top_level.txt
mamamiya-1.3.2.dist-info/RECORD
