Metadata-Version: 2.1
Name: mamamiya
Version: 1.3.2
Summary: A utility for crawling historical and Real-time Quotes data of China stocks
Home-page: http://mamamiya.org
Author: Jimmy Liu
Author-email: jimmysoa@sina.cn
License: BSD
Keywords: Global Financial Data
Classifier: Development Status :: 4 - Beta
Classifier: Programming Language :: Python :: 2.6
Classifier: Programming Language :: Python :: 2.7
Classifier: Programming Language :: Python :: 3.2
Classifier: Programming Language :: Python :: 3.3
Classifier: Programming Language :: Python :: 3.4
Classifier: Programming Language :: Python :: 3.5
Classifier: License :: OSI Approved :: BSD License
License-File: LICENSE
Requires-Dist: pandas (>=0.18.0)
Requires-Dist: requests (>=2.0.0)
Requires-Dist: lxml (>=3.8.0)
Requires-Dist: simplejson (>=3.16.0)
Requires-Dist: msgpack (>=0.5.6)
Requires-Dist: pyzmq (>=16.0.0)
